{
  "admin": {
    "password": "admin2026",
    "nombre": "admin",
    "expiracion": "2026-12-31"
  },
  "isis": {
    "password": "isis26",
    "nombre": "A. isis",
    "expiracion": "2026-05-15"
    },
  "yanet": {
    "password": "yanet26",
    "nombre": "M. Yanet",
    "expiracion": "2026-05-15"
    },
  "rey": {
    "password": "rey26",
    "nombre": "Rey",
    "expiracion": "2026-05-15"
  },
  "lisi": {
    "password": "lisi26",
    "nombre": "Lisandra",
    "expiracion": "2026-05-15"
  }
}





